README
setup.py
send_files/__init__.py
send_files/__main__.py
send_files/util.py
send_files.egg-info/PKG-INFO
send_files.egg-info/SOURCES.txt
send_files.egg-info/dependency_links.txt
send_files.egg-info/requires.txt
send_files.egg-info/top_level.txt
send_files/test/__init__.py
send_files/test/test_util.py