Metadata-Version: 1.1
Name: send-files
Version: 0.1
Summary: Copy files between computers.
Home-page: https://fritz.ftp.sh/fossil/send_files
Author: Fischers Fritz
Author-email: fischersfritz@sent.at
License: AGPL
Platform: UNKNOWN
Classifier: Programming Language :: Python :: 3.6
